aiojson/__init__.py
aiojson/client.py
aiojson/config.py
aiojson/exception.py
aiojson/middleware.py
aiojson/response.py
aiojson/routes.py
aiojson/template.py
tests/functional/__init__.py
tests/pytest/__init__.py
tests/pytest/test_middleware.py
tests/pytest/test_responses.py
tests/pytest/test_templates.py
aiojson-0.3.1612466996.dist-info/METADATA
aiojson-0.3.1612466996.dist-info/WHEEL
aiojson-0.3.1612466996.dist-info/top_level.txt
aiojson-0.3.1612466996.dist-info/RECORD
