Metadata-Version: 2.1
Name: aiojson
Version: 0.3.1612466996
Summary: Simple json request template validator for aiohttp
Home-page: https://git.yurzs.dev/yurzs/aiojson
Author: UNKNOWN
Author-email: UNKNOWN
License: UNKNOWN
Platform: UNKNOWN
Requires-Dist: aiohttp
